{
	"id": "76e75395-9442-454e-88e8-a5a785bddbe1",
	"name": "Qauto2",
	"values": [
		{
			"key": "BaseURL",
			"value": "https://qauto2.forstudy.space/api",
			"type": "default",
			"enabled": true
		},
		{
			"key": "password",
			"value": "Qwerty111",
			"type": "default",
			"enabled": false
		},
		{
			"key": "email",
			"value": "Andriy0011144@gmail.com",
			"type": "default",
			"enabled": false
		},
		{
			"key": "email1",
			"value": "Cherkasov1111@gmail.com",
			"type": "default",
			"enabled": false
		},
		{
			"key": "name",
			"value": "Andrew",
			"type": "default",
			"enabled": false
		},
		{
			"key": "lastName",
			"value": "Cherkasov",
			"type": "default",
			"enabled": false
		},
		{
			"key": "email",
			"value": "",
			"type": "any",
			"enabled": true
		}
	],
	"_postman_variable_scope": "environment",
	"_postman_exported_at": "2024-04-03T20:14:45.127Z",
	"_postman_exported_using": "Postman/10.24.11"
}